client.py
league_mcp_client-1.0.0.dist-info/METADATA
league_mcp_client-1.0.0.dist-info/WHEEL
league_mcp_client-1.0.0.dist-info/top_level.txt
league_mcp_client-1.0.0.dist-info/RECORD
