Metadata-Version: 2.4
Name: league-mcp-client
Version: 1.0.0
Summary: Add your description here
Requires-Python: >=3.12
Requires-Dist: gradio>=4.0.0
Requires-Dist: langchain-core>=0.3.8
Requires-Dist: langchain-google-genai>=2.0.0
Requires-Dist: langchain-mcp-adapters>=0.1.0
Requires-Dist: langgraph>=0.2.35
Requires-Dist: mcp>=1.9.4
Requires-Dist: pydantic>=2.0.0
Requires-Dist: python-dotenv>=1.1.0
